TexSoup/__init__.py
TexSoup/category.py
TexSoup/data.py
TexSoup/reader.py
TexSoup/tex.py
TexSoup/tokens.py
TexSoup/utils.py
texsoup_alt-0.3.1.dist-info/LICENSE
texsoup_alt-0.3.1.dist-info/METADATA
texsoup_alt-0.3.1.dist-info/WHEEL
texsoup_alt-0.3.1.dist-info/top_level.txt
texsoup_alt-0.3.1.dist-info/RECORD
