Metadata-Version: 2.1
Name: texsoup-alt
Version: 0.3.1
Summary: parses valid LaTeX and provides variety of Beautiful-Soup-esque methods and Pythonic idioms for iterating over and searching the parse tree
Home-page: https://github.com/fluiddyn/texsoup-alt
Download-URL: https://github.com/fluiddyn/texsoup-alt/archive/0.3.1.zip
Author: Alvin Wan
Author-email: hi@alvinwan.com
License: BSD
Classifier: Topic :: Utilities
Classifier: Intended Audience :: Developers
Classifier: Programming Language :: Python :: 3
Classifier: Topic :: Software Development :: Libraries
License-File: LICENSE
